cmr/__init__.py
cmr/py.typed
cmr/queries.py
python_cmr-0.12.0.dist-info/LICENSE
python_cmr-0.12.0.dist-info/METADATA
python_cmr-0.12.0.dist-info/WHEEL
python_cmr-0.12.0.dist-info/RECORD
