Metadata-Version: 2.1
Name: python-cmr
Version: 0.12.0
Summary: Python wrapper to the NASA Common Metadata Repository (CMR) API.
Home-page: https://github.com/nasa/python_cmr
License: MIT
Author: python_cmr
Author-email: nasa/python_cmr@github.com
Requires-Python: >=3.8.1,<4.0.0
Classifier: Development Status :: 4 - Beta
Classifier: Environment :: Console
Classifier: Framework :: IPython
Classifier: Intended Audience :: Science/Research
Classifier: License :: OSI Approved :: MIT License
Classifier: Operating System :: OS Independent
Classifier: Programming Language :: Python :: 3
Classifier: Programming Language :: Python :: 3.9
Classifier: Programming Language :: Python :: 3.10
Classifier: Programming Language :: Python :: 3.11
Classifier: Programming Language :: Python :: 3.12
Classifier: Programming Language :: Python :: 3.8
Classifier: Topic :: Software Development :: Libraries :: Python Modules
Classifier: Typing :: Typed
Requires-Dist: python-dateutil (>=2.8.2,<3.0.0)
Requires-Dist: requests (>=2.26.0,<3.0.0)
Requires-Dist: typing-extensions (>=4.11.0,<5.0.0)
Project-URL: Repository, https://github.com/nasa/python_cmr
